Workbook

Sheet Instrucciones
B2: Sistema Esmeralda — Plantilla de carga inicial
B3: Con estos datos se carga el sistema antes de empezar a usarlo. Todos los montos en córdobas (C$).
B5: Leyenda
C6: Celda para llenar
C7: Se calcula sola (no escribir)
B8: Ejemplo | C8: Texto gris en cursiva = fila de ejemplo (fila 2 de cada hoja): sobrescríbala o bórrela
B10: Orden sugerido
B11: 1. Categorias | C11: Revise la lista. Ya trae las categorías del negocio; puede agregar o cambiar nombres.
B12: 2. Gamas | C12: Solo lectura. Acero clásica y Acero de lujo usan tabla de precios; Titanio cobra servicio + pieza.
B13: 3. Perforaciones | C13: Una fila por tipo de perforación: código corto (2 a 6 letras, ej. HLX), nombre, precio de SOLO servicio, cuántas piezas lleva el paquete y qué gamas acepta.
B14: 4. PreciosPaquete | C14: Se llena sola con sus perforaciones. Escriba el precio del paquete CON pieza de acero clásica y de lujo. Titanio no lleva precio aquí.
B15: 5. PreciosEspeciales | C15: Opcional. Excepciones: un precio de paquete distinto para una pieza o gama concreta.
B16: 6. Productos | C16: Una fila por pieza o artículo que se vende (cada medida es una fila). SKU único. Gama solo para piezas de perforación.
B17: 7. InventarioInicial | C17: Cantidades que hay hoy en bodega y en cada sucursal, por SKU.
B18: 8. Proveedores | C18: A quién le compran y en qué moneda.
B19: 9. Usuarios | C19: Personas que usarán el sistema, con su rol y sucursal.
B20: 10. Promociones | C20: Opcional. Promociones que quiera dejar creadas (inactivas o activas).
B21: 11. Revision | C21: Revise que todo diga OK antes de enviar el archivo.
B23: Reglas importantes
C24: • El SKU identifica cada pieza y no se puede repetir. Sugerencia: MATERIAL-TIPO-CALIBRE-MEDIDA, ej. TIT-LAB-16-6.
C25: • Cada medida, color o diseño distinto es una fila distinta (labret 6 mm y labret 8 mm son dos SKU).
C26: • Código de barras: solo si la pieza ya trae uno del fabricante. Si no, déjelo vacío: el sistema imprime etiquetas QR.
C27: • Gama: solo para piezas que se usan en perforaciones. Perfumería, joyería de plata, NeilMed, etc. van sin gama.
C28: • Costo unitario: lo que le cuesta hoy cada pieza en C$ (con envío e impuestos si los conoce). Si no lo sabe, déjelo vacío.
C29: • El precio de venta es el precio establecido. En la venta se podrá cobrar más, nunca menos.
C30: • El paquete de titanio no lleva precio en la tabla: el sistema cobra el precio de solo servicio + el precio de la pieza.

Sheet Categorias
A1: Categoría | B1: Descripción (opcional)
A2: Perforaciones
A3: Piercing titanio
A4: Piercing acero
A5: Piercing bioflex
A6: Cuidado posterior
A7: Joyería plata 925
A8: Joyería xuping
A9: Joyería estilo Dubái
A10: Accesorios dama
A11: Accesorios caballero
A12: Perfumería

Sheet Gamas
A1: Gama | B1: Cómo se cobra el paquete | C1: Ejemplo
A2: Acero clásica | B2: Precio fijo por perforación (tabla) | C2: Hélix con pieza clásica = precio de la tabla
A3: Acero de lujo | B3: Precio fijo por perforación (tabla) | C3: Hélix con pieza de lujo = precio de la tabla
A4: Titanio | B4: Precio de solo servicio + precio de la pieza | C4: Hélix (350) + labret de titanio (650) = 1,000

Sheet Perforaciones
A1: Código * (2 a 6 letras) | B1: Nombre * | C1: Precio SOLO servicio (C$) * | D1: Piezas por paquete * | E1: ¿Acepta Acero clásica? | F1: ¿Acepta Acero de lujo? | G1: ¿Acepta Titanio? | H1: Notas
A2: HLX | B2: Hélix | C2: 350 | D2: 1 | E2: Sí | F2: Sí | G2: Sí | H2: Ejemplo: hélix

Sheet PreciosPaquete
A1: Código | B1: Perforación | C1: Solo servicio (C$) | D1: Con pieza ACERO CLÁSICA (C$) | E1: Con pieza ACERO DE LUJO (C$) | F1: Con pieza TITANIO | G1: Estado
A2: =IF(Perforaciones!A2="","",Perforaciones!A2) -> HLX | B2: =IF(Perforaciones!A2="","",Perforaciones!B2) -> Hélix | C2: =IF(Perforaciones!A2="","",Perforaciones!C2) -> 350 | D2: 450 | E2: 550 | F2: =IF(Perforaciones!A2="","",IF(Perforaciones!G2="Sí","Servicio + precio de la pieza","No acepta titanio")) -> Servicio + precio de la pieza | G2: =IF(Perforaciones!A2="","",IF(AND(Perforaciones!E2="Sí",D2=""),"Falta precio clásica",IF(AND(Perforaciones!F2="Sí",E2=""),"Falta precio lujo","OK"))) -> OK
A3: =IF(Perforaciones!A3="","",Perforaciones!A3) | B3: =IF(Perforaciones!A3="","",Perforaciones!B3) | C3: =IF(Perforaciones!A3="","",Perforaciones!C3) | F3: =IF(Perforaciones!A3="","",IF(Perforaciones!G3="Sí","Servicio + precio de la pieza","No acepta titanio")) | G3: =IF(Perforaciones!A3="","",IF(AND(Perforaciones!E3="Sí",D3=""),"Falta precio clásica",IF(AND(Perforaciones!F3="Sí",E3=""),"Falta precio lujo","OK")))
A4: =IF(Perforaciones!A4="","",Perforaciones!A4) | B4: =IF(Perforaciones!A4="","",Perforaciones!B4) | C4: =IF(Perforaciones!A4="","",Perforaciones!C4) | F4: =IF(Perforaciones!A4="","",IF(Perforaciones!G4="Sí","Servicio + precio de la pieza","No acepta titanio")) | G4: =IF(Perforaciones!A4="","",IF(AND(Perforaciones!E4="Sí",D4=""),"Falta precio clásica",IF(AND(Perforaciones!F4="Sí",E4=""),"Falta precio lujo","OK")))
A5: =IF(Perforaciones!A5="","",Perforaciones!A5) | B5: =IF(Perforaciones!A5="","",Perforaciones!B5) | C5: =IF(Perforaciones!A5="","",Perforaciones!C5) | F5: =IF(Perforaciones!A5="","",IF(Perforaciones!G5="Sí","Servicio + precio de la pieza","No acepta titanio")) | G5: =IF(Perforaciones!A5="","",IF(AND(Perforaciones!E5="Sí",D5=""),"Falta precio clásica",IF(AND(Perforaciones!F5="Sí",E5=""),"Falta precio lujo","OK")))
A6: =IF(Perforaciones!A6="","",Perforaciones!A6) | B6: =IF(Perforaciones!A6="","",Perforaciones!B6) | C6: =IF(Perforaciones!A6="","",Perforaciones!C6) | F6: =IF(Perforaciones!A6="","",IF(Perforaciones!G6="Sí","Servicio + precio de la pieza","No acepta titanio")) | G6: =IF(Perforaciones!A6="","",IF(AND(Perforaciones!E6="Sí",D6=""),"Falta precio clásica",IF(AND(Perforaciones!F6="Sí",E6=""),"Falta precio lujo","OK")))
A7: =IF(Perforaciones!A7="","",Perforaciones!A7) | B7: =IF(Perforaciones!A7="","",Perforaciones!B7) | C7: =IF(Perforaciones!A7="","",Perforaciones!C7) | F7: =IF(Perforaciones!A7="","",IF(Perforaciones!G7="Sí","Servicio + precio de la pieza","No acepta titanio")) | G7: =IF(Perforaciones!A7="","",IF(AND(Perforaciones!E7="Sí",D7=""),"Falta precio clásica",IF(AND(Perforaciones!F7="Sí",E7=""),"Falta precio lujo","OK")))
A8: =IF(Perforaciones!A8="","",Perforaciones!A8) | B8: =IF(Perforaciones!A8="","",Perforaciones!B8) | C8: =IF(Perforaciones!A8="","",Perforaciones!C8) | F8: =IF(Perforaciones!A8="","",IF(Perforaciones!G8="Sí","Servicio + precio de la pieza","No acepta titanio")) | G8: =IF(Perforaciones!A8="","",IF(AND(Perforaciones!E8="Sí",D8=""),"Falta precio clásica",IF(AND(Perforaciones!F8="Sí",E8=""),"Falta precio lujo","OK")))
A9: =IF(Perforaciones!A9="","",Perforaciones!A9) | B9: =IF(Perforaciones!A9="","",Perforaciones!B9) | C9: =IF(Perforaciones!A9="","",Perforaciones!C9) | F9: =IF(Perforaciones!A9="","",IF(Perforaciones!G9="Sí","Servicio + precio de la pieza","No acepta titanio")) | G9: =IF(Perforaciones!A9="","",IF(AND(Perforaciones!E9="Sí",D9=""),"Falta precio clásica",IF(AND(Perforaciones!F9="Sí",E9=""),"Falta precio lujo","OK")))
A10: =IF(Perforaciones!A10="","",Perforaciones!A10) | B10: =IF(Perforaciones!A10="","",Perforaciones!B10) | C10: =IF(Perforaciones!A10="","",Perforaciones!C10) | F10: =IF(Perforaciones!A10="","",IF(Perforaciones!G10="Sí","Servicio + precio de la pieza","No acepta titanio")) | G10: =IF(Perforaciones!A10="","",IF(AND(Perforaciones!E10="Sí",D10=""),"Falta precio clásica",IF(AND(Perforaciones!F10="Sí",E10=""),"Falta precio lujo","OK")))
A11: =IF(Perforaciones!A11="","",Perforaciones!A11) | B11: =IF(Perforaciones!A11="","",Perforaciones!B11) | C11: =IF(Perforaciones!A11="","",Perforaciones!C11) | F11: =IF(Perforaciones!A11="","",IF(Perforaciones!G11="Sí","Servicio + precio de la pieza","No acepta titanio")) | G11: =IF(Perforaciones!A11="","",IF(AND(Perforaciones!E11="Sí",D11=""),"Falta precio clásica",IF(AND(Perforaciones!F11="Sí",E11=""),"Falta precio lujo","OK")))
A12: =IF(Perforaciones!A12="","",Perforaciones!A12) | B12: =IF(Perforaciones!A12="","",Perforaciones!B12) | C12: =IF(Perforaciones!A12="","",Perforaciones!C12) | F12: =IF(Perforaciones!A12="","",IF(Perforaciones!G12="Sí","Servicio + precio de la pieza","No acepta titanio")) | G12: =IF(Perforaciones!A12="","",IF(AND(Perforaciones!E12="Sí",D12=""),"Falta precio clásica",IF(AND(Perforaciones!F12="Sí",E12=""),"Falta precio lujo","OK")))
A13: =IF(Perforaciones!A13="","",Perforaciones!A13) | B13: =IF(Perforaciones!A13="","",Perforaciones!B13) | C13: =IF(Perforaciones!A13="","",Perforaciones!C13) | F13: =IF(Perforaciones!A13="","",IF(Perforaciones!G13="Sí","Servicio + precio de la pieza","No acepta titanio")) | G13: =IF(Perforaciones!A13="","",IF(AND(Perforaciones!E13="Sí",D13=""),"Falta precio clásica",IF(AND(Perforaciones!F13="Sí",E13=""),"Falta precio lujo","OK")))
A14: =IF(Perforaciones!A14="","",Perforaciones!A14) | B14: =IF(Perforaciones!A14="","",Perforaciones!B14) | C14: =IF(Perforaciones!A14="","",Perforaciones!C14) | F14: =IF(Perforaciones!A14="","",IF(Perforaciones!G14="Sí","Servicio + precio de la pieza","No acepta titanio")) | G14: =IF(Perforaciones!A14="","",IF(AND(Perforaciones!E14="Sí",D14=""),"Falta precio clásica",IF(AND(Perforaciones!F14="Sí",E14=""),"Falta precio lujo","OK")))
... A61: =IF(Perforaciones!A61="","",Perforaciones!A61) | B61: =IF(Perforaciones!A61="","",Perforaciones!B61) | C61: =IF(Perforaciones!A61="","",Perforaciones!C61) | F61: =IF(Perforaciones!A61="","",IF(Perforaciones!G61="Sí","Servicio + precio de la pieza","No acepta titanio")) | G61: =IF(Perforaciones!A61="","",IF(AND(Perforaciones!E61="Sí",D61=""),"Falta precio clásica",IF(AND(Perforaciones!F61="Sí",E61=""),"Falta precio lujo","OK")))

Sheet PreciosEspeciales
A1: Perforación (código) * | B1: SKU de la pieza | C1: o Gama | D1: Precio del paquete (C$) * | E1: Motivo
A2: HLX | B2: TIT-LAB-16-8 | D2: 900 | E2: Ejemplo: precio de lanzamiento

Sheet Productos
A1: SKU * | B1: Código de barras (si trae) | C1: Categoría * | D1: Producto * | E1: Variante / medida * | F1: Material | G1: Calibre | H1: Largo o diámetro (mm) | I1: Gama (solo piezas de perforación) | J1: Precio de venta (C$) * | K1: Costo unitario (C$) | L1: Stock mínimo Las Américas | M1: Stock mínimo Las Brisas | N1: Margen | O1: Notas
A2: TIT-LAB-16-6 | C2: Piercing titanio | D2: Labret rosca interna | E2: Titanio F-136 · 16G · 6 mm | F2: Titanio ASTM F-136 | G2: 16G | H2: 6 | I2: Titanio | J2: 650 | K2: 220 | L2: 5 | M2: 5 | N2: =IF(OR(J2="",K2="",J2=0),"",(J2-K2)/J2) -> 0.66153846 | O2: Ejemplo
N3: =IF(OR(J3="",K3="",J3=0),"",(J3-K3)/J3)
N4: =IF(OR(J4="",K4="",J4=0),"",(J4-K4)/J4)
N5: =IF(OR(J5="",K5="",J5=0),"",(J5-K5)/J5)
N6: =IF(OR(J6="",K6="",J6=0),"",(J6-K6)/J6)
N7: =IF(OR(J7="",K7="",J7=0),"",(J7-K7)/J7)
N8: =IF(OR(J8="",K8="",J8=0),"",(J8-K8)/J8)
N9: =IF(OR(J9="",K9="",J9=0),"",(J9-K9)/J9)
N10: =IF(OR(J10="",K10="",J10=0),"",(J10-K10)/J10)
N11: =IF(OR(J11="",K11="",J11=0),"",(J11-K11)/J11)
N12: =IF(OR(J12="",K12="",J12=0),"",(J12-K12)/J12)
N13: =IF(OR(J13="",K13="",J13=0),"",(J13-K13)/J13)
N14: =IF(OR(J14="",K14="",J14=0),"",(J14-K14)/J14)
... N1001: =IF(OR(J1001="",K1001="",J1001=0),"",(J1001-K1001)/J1001)

Sheet InventarioInicial
A1: SKU * | B1: Producto | C1: Bodega central | D1: Las Américas | E1: Las Brisas | F1: Total | G1: Costo unitario (C$) | H1: Valor a costo (C$)
A2: TIT-LAB-16-6 | B2: =IF(A2="","",IFERROR(INDEX(Productos!$D$2:$D$1001,MATCH(A2,Productos!$A$2:$A$1001,0))&" — "&INDEX(Productos!$E$2:$E$1001,MATCH(A2,Productos!$A$2:$A$1001,0)),"SKU no existe en Productos")) -> Labret rosca interna — Titanio F-136 · 16G · 6 mm | C2: 10 | D2: 20 | E2: 10 | F2: =IF(A2="","",SUM(C2:E2)) -> 40 | G2: =IF(A2="","",IFERROR(INDEX(Productos!$K$2:$K$1001,MATCH(A2,Productos!$A$2:$A$1001,0)),"")) -> 220 | H2: =IF(OR(A2="",G2=""),"",F2*G2) -> 8800
B3: =IF(A3="","",IFERROR(INDEX(Productos!$D$2:$D$1001,MATCH(A3,Productos!$A$2:$A$1001,0))&" — "&INDEX(Productos!$E$2:$E$1001,MATCH(A3,Productos!$A$2:$A$1001,0)),"SKU no existe en Productos")) | F3: =IF(A3="","",SUM(C3:E3)) | G3: =IF(A3="","",IFERROR(INDEX(Productos!$K$2:$K$1001,MATCH(A3,Productos!$A$2:$A$1001,0)),"")) | H3: =IF(OR(A3="",G3=""),"",F3*G3)
B4: =IF(A4="","",IFERROR(INDEX(Productos!$D$2:$D$1001,MATCH(A4,Productos!$A$2:$A$1001,0))&" — "&INDEX(Productos!$E$2:$E$1001,MATCH(A4,Productos!$A$2:$A$1001,0)),"SKU no existe en Productos")) | F4: =IF(A4="","",SUM(C4:E4)) | G4: =IF(A4="","",IFERROR(INDEX(Productos!$K$2:$K$1001,MATCH(A4,Productos!$A$2:$A$1001,0)),"")) | H4: =IF(OR(A4="",G4=""),"",F4*G4)
B5: =IF(A5="","",IFERROR(INDEX(Productos!$D$2:$D$1001,MATCH(A5,Productos!$A$2:$A$1001,0))&" — "&INDEX(Productos!$E$2:$E$1001,MATCH(A5,Productos!$A$2:$A$1001,0)),"SKU no existe en Productos")) | F5: =IF(A5="","",SUM(C5:E5)) | G5: =IF(A5="","",IFERROR(INDEX(Productos!$K$2:$K$1001,MATCH(A5,Productos!$A$2:$A$1001,0)),"")) | H5: =IF(OR(A5="",G5=""),"",F5*G5)
B6: =IF(A6="","",IFERROR(INDEX(Productos!$D$2:$D$1001,MATCH(A6,Productos!$A$2:$A$1001,0))&" — "&INDEX(Productos!$E$2:$E$1001,MATCH(A6,Productos!$A$2:$A$1001,0)),"SKU no existe en Productos")) | F6: =IF(A6="","",SUM(C6:E6)) | G6: =IF(A6="","",IFERROR(INDEX(Productos!$K$2:$K$1001,MATCH(A6,Productos!$A$2:$A$1001,0)),"")) | H6: =IF(OR(A6="",G6=""),"",F6*G6)
B7: =IF(A7="","",IFERROR(INDEX(Productos!$D$2:$D$1001,MATCH(A7,Productos!$A$2:$A$1001,0))&" — "&INDEX(Productos!$E$2:$E$1001,MATCH(A7,Productos!$A$2:$A$1001,0)),"SKU no existe en Productos")) | F7: =IF(A7="","",SUM(C7:E7)) | G7: =IF(A7="","",IFERROR(INDEX(Productos!$K$2:$K$1001,MATCH(A7,Productos!$A$2:$A$1001,0)),"")) | H7: =IF(OR(A7="",G7=""),"",F7*G7)
B8: =IF(A8="","",IFERROR(INDEX(Productos!$D$2:$D$1001,MATCH(A8,Productos!$A$2:$A$1001,0))&" — "&INDEX(Productos!$E$2:$E$1001,MATCH(A8,Productos!$A$2:$A$1001,0)),"SKU no existe en Productos")) | F8: =IF(A8="","",SUM(C8:E8)) | G8: =IF(A8="","",IFERROR(INDEX(Productos!$K$2:$K$1001,MATCH(A8,Productos!$A$2:$A$1001,0)),"")) | H8: =IF(OR(A8="",G8=""),"",F8*G8)
B9: =IF(A9="","",IFERROR(INDEX(Productos!$D$2:$D$1001,MATCH(A9,Productos!$A$2:$A$1001,0))&" — "&INDEX(Productos!$E$2:$E$1001,MATCH(A9,Productos!$A$2:$A$1001,0)),"SKU no existe en Productos")) | F9: =IF(A9="","",SUM(C9:E9)) | G9: =IF(A9="","",IFERROR(INDEX(Productos!$K$2:$K$1001,MATCH(A9,Productos!$A$2:$A$1001,0)),"")) | H9: =IF(OR(A9="",G9=""),"",F9*G9)
B10: =IF(A10="","",IFERROR(INDEX(Productos!$D$2:$D$1001,MATCH(A10,Productos!$A$2:$A$1001,0))&" — "&INDEX(Productos!$E$2:$E$1001,MATCH(A10,Productos!$A$2:$A$1001,0)),"SKU no existe en Productos")) | F10: =IF(A10="","",SUM(C10:E10)) | G10: =IF(A10="","",IFERROR(INDEX(Productos!$K$2:$K$1001,MATCH(A10,Productos!$A$2:$A$1001,0)),"")) | H10: =IF(OR(A10="",G10=""),"",F10*G10)
B11: =IF(A11="","",IFERROR(INDEX(Productos!$D$2:$D$1001,MATCH(A11,Productos!$A$2:$A$1001,0))&" — "&INDEX(Productos!$E$2:$E$1001,MATCH(A11,Productos!$A$2:$A$1001,0)),"SKU no existe en Productos")) | F11: =IF(A11="","",SUM(C11:E11)) | G11: =IF(A11="","",IFERROR(INDEX(Productos!$K$2:$K$1001,MATCH(A11,Productos!$A$2:$A$1001,0)),"")) | H11: =IF(OR(A11="",G11=""),"",F11*G11)
B12: =IF(A12="","",IFERROR(INDEX(Productos!$D$2:$D$1001,MATCH(A12,Productos!$A$2:$A$1001,0))&" — "&INDEX(Productos!$E$2:$E$1001,MATCH(A12,Productos!$A$2:$A$1001,0)),"SKU no existe en Productos")) | F12: =IF(A12="","",SUM(C12:E12)) | G12: =IF(A12="","",IFERROR(INDEX(Productos!$K$2:$K$1001,MATCH(A12,Productos!$A$2:$A$1001,0)),"")) | H12: =IF(OR(A12="",G12=""),"",F12*G12)
B13: =IF(A13="","",IFERROR(INDEX(Productos!$D$2:$D$1001,MATCH(A13,Productos!$A$2:$A$1001,0))&" — "&INDEX(Productos!$E$2:$E$1001,MATCH(A13,Productos!$A$2:$A$1001,0)),"SKU no existe en Productos")) | F13: =IF(A13="","",SUM(C13:E13)) | G13: =IF(A13="","",IFERROR(INDEX(Productos!$K$2:$K$1001,MATCH(A13,Productos!$A$2:$A$1001,0)),"")) | H13: =IF(OR(A13="",G13=""),"",F13*G13)
B14: =IF(A14="","",IFERROR(INDEX(Productos!$D$2:$D$1001,MATCH(A14,Productos!$A$2:$A$1001,0))&" — "&INDEX(Productos!$E$2:$E$1001,MATCH(A14,Productos!$A$2:$A$1001,0)),"SKU no existe en Productos")) | F14: =IF(A14="","",SUM(C14:E14)) | G14: =IF(A14="","",IFERROR(INDEX(Productos!$K$2:$K$1001,MATCH(A14,Productos!$A$2:$A$1001,0)),"")) | H14: =IF(OR(A14="",G14=""),"",F14*G14)
... B1001: =IF(A1001="","",IFERROR(INDEX(Productos!$D$2:$D$1001,MATCH(A1001,Productos!$A$2:$A$1001,0))&" — "&INDEX(Productos!$E$2:$E$1001,MATCH(A1001,Productos!$A$2:$A$1001,0)),"SKU no existe en Productos")) | F1001: =IF(A1001="","",SUM(C1001:E1001)) | G1001: =IF(A1001="","",IFERROR(INDEX(Productos!$K$2:$K$1001,MATCH(A1001,Productos!$A$2:$A$1001,0)),"")) | H1001: =IF(OR(A1001="",G1001=""),"",F1001*G1001)

Sheet Proveedores
A1: Nombre * | B1: País | C1: Moneda habitual * | D1: Contacto | E1: Teléfono | F1: Correo
A2: Distribuidora de ejemplo | B2: Estados Unidos | C2: USD | D2: Nombre del contacto

Sheet Usuarios
A1: Nombre completo * | B1: Usuario * (minúsculas, sin espacios) | C1: Rol * | D1: Sucursal * | E1: Correo | F1: Teléfono
A2: María López | B2: maria.lopez | C2: Encargado | D2: Las Américas

Sheet Promociones
A1: Nombre * | B1: Tipo * | C1: Valor * (% o C$) | D1: Compra mínima (C$) | E1: Válida desde | F1: Válida hasta | G1: ¿Activa? | H1: Descripción
A2: Promo 10 % | B2: PORCENTAJE | C2: 10 | D2: 0 | G2: No | H2: 10 % en toda la venta

Sheet Revision
B2: Revisión antes de enviar
B3: Todo debe decir OK. Las cifras se actualizan solas.
B5: Revisión | C5: Cantidad | D5: Estado
B6: SKU repetidos en Productos | C6: =SUMPRODUCT((Productos!$A$2:$A$1001<>"")*(COUNTIF(Productos!$A$2:$A$1001,Productos!$A$2:$A$1001)>1)) -> 0 | D6: =IF(C6=0,"OK","Revisar") -> OK
B7: Productos sin categoría | C7: =COUNTIFS(Productos!$A$2:$A$1001,"<>",Productos!$C$2:$C$1001,"") -> 0 | D7: =IF(C7=0,"OK","Revisar") -> OK
B8: Productos sin precio de venta | C8: =COUNTIFS(Productos!$A$2:$A$1001,"<>",Productos!$J$2:$J$1001,"") -> 0 | D8: =IF(C8=0,"OK","Revisar") -> OK
B9: Piezas de piercing sin gama | C9: =COUNTIFS(Productos!$A$2:$A$1001,"<>",Productos!$C$2:$C$1001,"Piercing*",Productos!$I$2:$I$1001,"") -> 0 | D9: =IF(C9=0,"OK","Revisar") -> OK
B10: Productos con margen menor a 40 % | C10: =COUNTIFS(Productos!$N$2:$N$1001,"<0.4") -> 0 | D10: =IF(C10=0,"OK","Revisar") -> OK
B11: SKU de inventario que no existen en Productos | C11: =COUNTIF(InventarioInicial!$B$2:$B$1001,"SKU no existe*") -> 0 | D11: =IF(C11=0,"OK","Revisar") -> OK
B12: Perforaciones con precio faltante en la tabla | C12: =COUNTIF(PreciosPaquete!$G$2:$G$61,"Falta*") -> 0 | D12: =IF(C12=0,"OK","Revisar") -> OK
B13: Códigos de perforación repetidos | C13: =SUMPRODUCT((Perforaciones!$A$2:$A$61<>"")*(COUNTIF(Perforaciones!$A$2:$A$61,Perforaciones!$A$2:$A$61)>1)) -> 0 | D13: =IF(C13=0,"OK","Revisar") -> OK
B14: Usuarios repetidos | C14: =SUMPRODUCT((Usuarios!$B$2:$B$51<>"")*(COUNTIF(Usuarios!$B$2:$B$51,Usuarios!$B$2:$B$51)>1)) -> 0 | D14: =IF(C14=0,"OK","Revisar") -> OK
B15: Productos cargados | C15: =COUNTA(Productos!$A$2:$A$1001) -> 1
B16: Perforaciones cargadas | C16: =COUNTA(Perforaciones!$A$2:$A$61) -> 1
B17: Piezas en inventario inicial (total) | C17: =SUM(InventarioInicial!$C$2:$E$1001) -> 40
B18: Valor del inventario inicial a costo (C$) | C18: =SUM(InventarioInicial!$H$2:$H$1001) -> 8800
B20: Las filas de ejemplo (fila 2, en gris) cuentan como datos: bórrelas o reemplácelas antes de enviar.
